{
  "id": "negative",
  "order": 5,
  "direction": "构图",
  "category": "留白",
  "subcategory": "负空间",
  "en": "NEGATIVE SPACE",
  "difficulty": "进阶",
  "tags": [
    "负空间",
    "留白",
    "主体大小",
    "极简",
    "呼吸感",
    "飞鸟"
  ],
  "title": "这只鸟该多大?",
  "hint": "同一只海鸥,两种取景。",
  "svg": {
    "good": "<rect width=\"600\" height=\"400\" fill=\"url(#mist)\"/>${gull(470,90,1)}${gull(505,118,0.6)}${grain}",
    "bad": "<rect width=\"600\" height=\"400\" fill=\"url(#mist)\"/>${gull(300,200,3.4)}${grain}"
  },
  "verdict": "更有意境的是把鸟放小、留出大片天空的一张。",
  "points": [
    "适度的负空间(留白)反而凸显主体,给画面安静、辽阔的呼吸感,情绪一下就出来了。",
    "把主体放大塞满中央,信息是清楚了,但局促、平淡,失去了想象的余地。"
  ],
  "soft": {
    "label": "并非定律",
    "text": "特写、纪实里「塞满」是力量。但写意、极简的题材,留白往往更动人。"
  }
}
